{
  "device": "openaps://indy-e1", 
  "pump": {
    "battery": {
      "status": "normal", 
      "voltage": 1.55
    }, 
    "status": {
      "status": "normal", 
      "timestamp": "2016-06-15T03:30:54.000Z", 
      "bolusing": false, 
      "suspended": false
    }, 
    "reservoir": 111.975, 
    "clock": "2016-06-14T20:30:24-07:00"
  }, 
  "openaps": {
    "suggested": {
      "bg": 157, 
      "temp": "absolute", 
      "snoozeBG": 15, 
      "timestamp": "2016-06-15T03:32:07.000Z", 
      "predBGs": {
        "aCOB": [
          157, 
          153, 
          149, 
          144, 
          139, 
          135, 
          131, 
          127, 
          124, 
          122, 
          120, 
          120, 
          120, 
          120, 
          121, 
          122, 
          124, 
          125, 
          128, 
          130, 
          133, 
          135, 
          138, 
          141, 
          143, 
          146, 
          148, 
          150, 
          152, 
          153, 
          154, 
          154, 
          155, 
          155, 
          156
        ], 
        "IOB": [
          157, 
          143, 
          130, 
          116, 
          103, 
          90, 
          77, 
          66, 
          56, 
          47, 
          39, 
          39, 
          39
        ]
      }, 
      "reason": "COB: 36, Dev: -5, BGI: -10.24, ISF: 67.8, Target: 107; Eventual BG 15<107, setting -4.598U/hr, but 26m left and 0 ~ req 0U/hr: no action required", 
      "COB": 36, 
      "eventualBG": 15, 
      "tick": -14, 
      "IOB": 2.027
    }, 
    "iob": [
      {
        "netbasalinsulin": 0.2, 
        "activity": 0.0302, 
        "basaliob": 0.356, 
        "time": "2016-06-15T03:30:24.000Z", 
        "hightempinsulin": 1.1, 
        "bolussnooze": 0, 
        "iob": 2.027
      }, 
      {
        "netbasalinsulin": 0.2, 
        "activity": 0.031, 
        "basaliob": 0.222, 
        "time": "2016-06-15T03:35:24.000Z", 
        "hightempinsulin": 1.1, 
        "bolussnooze": 0, 
        "iob": 1.773
      }, 
      {
        "netbasalinsulin": 0.2, 
        "activity": 0.0315, 
        "basaliob": 0.139, 
        "time": "2016-06-15T03:40:24.000Z", 
        "hightempinsulin": 1.1, 
        "bolussnooze": 0, 
        "iob": 1.565
      }, 
      {
        "netbasalinsulin": 0.2, 
        "activity": 0.0319, 
        "basaliob": 0.056, 
        "time": "2016-06-15T03:45:24.000Z", 
        "hightempinsulin": 1.1, 
        "bolussnooze": 0, 
        "iob": 1.355
      }, 
      {
        "netbasalinsulin": 0.2, 
        "activity": 0.0321, 
        "basaliob": -0.024, 
        "time": "2016-06-15T03:50:24.000Z", 
        "hightempinsulin": 1.1, 
        "bolussnooze": 0, 
        "iob": 1.144
      }, 
      {
        "netbasalinsulin": 0.2, 
        "activity": 0.0303, 
        "basaliob": -0.103, 
        "time": "2016-06-15T03:55:24.000Z", 
        "hightempinsulin": 1.1, 
        "bolussnooze": 0, 
        "iob": 0.943
      }, 
      {
        "netbasalinsulin": 0.2, 
        "activity": 0.0285, 
        "basaliob": -0.13, 
        "time": "2016-06-15T04:00:24.000Z", 
        "hightempinsulin": 1.1, 
        "bolussnooze": 0, 
        "iob": 0.8
      }, 
      {
        "netbasalinsulin": 0.2, 
        "activity": 0.0266, 
        "basaliob": -0.154, 
        "time": "2016-06-15T04:05:24.000Z", 
        "hightempinsulin": 1.1, 
        "bolussnooze": 0, 
        "iob": 0.667
      }, 
      {
        "netbasalinsulin": 0.25, 
        "activity": 0.0246, 
        "basaliob": -0.175, 
        "time": "2016-06-15T04:10:24.000Z", 
        "hightempinsulin": 1.1, 
        "bolussnooze": 0, 
        "iob": 0.544
      }, 
      {
        "netbasalinsulin": 0.25, 
        "activity": 0.0224, 
        "basaliob": -0.192, 
        "time": "2016-06-15T04:15:24.000Z", 
        "hightempinsulin": 1.1, 
        "bolussnooze": 0, 
        "iob": 0.432
      }, 
      {
        "netbasalinsulin": 0.3, 
        "activity": 0.0202, 
        "basaliob": -0.205, 
        "time": "2016-06-15T04:20:24.000Z", 
        "hightempinsulin": 1.1, 
        "bolussnooze": 0, 
        "iob": 0.331
      }, 
      {
        "netbasalinsulin": 0.35, 
        "activity": 0.018, 
        "basaliob": -0.214, 
        "time": "2016-06-15T04:25:24.000Z", 
        "hightempinsulin": 1.1, 
        "bolussnooze": 0, 
        "iob": 0.242
      }, 
      {
        "netbasalinsulin": 0.4, 
        "activity": 0.0158, 
        "basaliob": -0.22, 
        "time": "2016-06-15T04:30:24.000Z", 
        "hightempinsulin": 1.1, 
        "bolussnooze": 0, 
        "iob": 0.163
      }, 
      {
        "netbasalinsulin": 0.45, 
        "activity": 0.0136, 
        "basaliob": -0.221, 
        "time": "2016-06-15T04:35:24.000Z", 
        "hightempinsulin": 1.1, 
        "bolussnooze": 0, 
        "iob": 0.095
      }, 
      {
        "netbasalinsulin": 0.5, 
        "activity": 0.0115, 
        "basaliob": -0.219, 
        "time": "2016-06-15T04:40:24.000Z", 
        "hightempinsulin": 1.1, 
        "bolussnooze": 0, 
        "iob": 0.037
      }, 
      {
        "netbasalinsulin": 0.5, 
        "activity": 0.0094, 
        "basaliob": -0.213, 
        "time": "2016-06-15T04:45:24.000Z", 
        "hightempinsulin": 1.05, 
        "bolussnooze": 0, 
        "iob": -0.01
      }, 
      {
        "netbasalinsulin": 0.45, 
        "activity": 0.0074, 
        "basaliob": -0.204, 
        "time": "2016-06-15T04:50:24.000Z", 
        "hightempinsulin": 1, 
        "bolussnooze": 0, 
        "iob": -0.047
      }, 
      {
        "netbasalinsulin": 0.4, 
        "activity": 0.0056, 
        "basaliob": -0.193, 
        "time": "2016-06-15T04:55:24.000Z", 
        "hightempinsulin": 0.95, 
        "bolussnooze": 0, 
        "iob": -0.075
      }, 
      {
        "netbasalinsulin": 0.35, 
        "activity": 0.0038, 
        "basaliob": -0.181, 
        "time": "2016-06-15T05:00:24.000Z", 
        "hightempinsulin": 0.9, 
        "bolussnooze": 0, 
        "iob": -0.093
      }, 
      {
        "netbasalinsulin": 0.25, 
        "activity": 0.0023, 
        "basaliob": -0.166, 
        "time": "2016-06-15T05:05:24.000Z", 
        "hightempinsulin": 0.8, 
        "bolussnooze": 0, 
        "iob": -0.105
      }, 
      {
        "netbasalinsulin": 0.15, 
        "activity": 0.0012, 
        "basaliob": -0.152, 
        "time": "2016-06-15T05:10:24.000Z", 
        "hightempinsulin": 0.7, 
        "bolussnooze": 0, 
        "iob": -0.111
      }, 
      {
        "netbasalinsulin": 0, 
        "activity": 0.0004, 
        "basaliob": -0.137, 
        "time": "2016-06-15T05:15:24.000Z", 
        "hightempinsulin": 0.55, 
        "bolussnooze": 0, 
        "iob": -0.112
      }, 
      {
        "netbasalinsulin": -0.1, 
        "activity": -0.0005, 
        "basaliob": -0.122, 
        "time": "2016-06-15T05:20:24.000Z", 
        "hightempinsulin": 0.45, 
        "bolussnooze": 0, 
        "iob": -0.11
      }, 
      {
        "netbasalinsulin": -0.2, 
        "activity": -0.0012, 
        "basaliob": -0.108, 
        "time": "2016-06-15T05:25:24.000Z", 
        "hightempinsulin": 0.35, 
        "bolussnooze": 0, 
        "iob": -0.104
      }, 
      {
        "netbasalinsulin": -0.25, 
        "activity": -0.002, 
        "basaliob": -0.094, 
        "time": "2016-06-15T05:30:24.000Z", 
        "hightempinsulin": 0.3, 
        "bolussnooze": 0, 
        "iob": -0.094
      }, 
      {
        "netbasalinsulin": -0.25, 
        "activity": -0.0026, 
        "basaliob": -0.081, 
        "time": "2016-06-15T05:35:24.000Z", 
        "hightempinsulin": 0.3, 
        "bolussnooze": 0, 
        "iob": -0.081
      }, 
      {
        "netbasalinsulin": -0.25, 
        "activity": -0.0025, 
        "basaliob": -0.069, 
        "time": "2016-06-15T05:40:24.000Z", 
        "hightempinsulin": 0.3, 
        "bolussnooze": 0, 
        "iob": -0.069
      }, 
      {
        "netbasalinsulin": -0.25, 
        "activity": -0.0023, 
        "basaliob": -0.057, 
        "time": "2016-06-15T05:45:24.000Z", 
        "hightempinsulin": 0.3, 
        "bolussnooze": 0, 
        "iob": -0.057
      }, 
      {
        "netbasalinsulin": -0.35, 
        "activity": -0.0022, 
        "basaliob": -0.046, 
        "time": "2016-06-15T05:50:24.000Z", 
        "hightempinsulin": 0.2, 
        "bolussnooze": 0, 
        "iob": -0.046
      }, 
      {
        "netbasalinsulin": -0.45, 
        "activity": -0.002, 
        "basaliob": -0.036, 
        "time": "2016-06-15T05:55:24.000Z", 
        "hightempinsulin": 0.1, 
        "bolussnooze": 0, 
        "iob": -0.036
      }, 
      {
        "netbasalinsulin": -0.5, 
        "activity": -0.0017, 
        "basaliob": -0.028, 
        "time": "2016-06-15T06:00:24.000Z", 
        "hightempinsulin": 0.05, 
        "bolussnooze": 0, 
        "iob": -0.028
      }, 
      {
        "netbasalinsulin": -0.5, 
        "activity": -0.0014, 
        "basaliob": -0.02, 
        "time": "2016-06-15T06:05:24.000Z", 
        "hightempinsulin": 0, 
        "bolussnooze": 0, 
        "iob": -0.02
      }, 
      {
        "netbasalinsulin": -0.5, 
        "activity": -0.0012, 
        "basaliob": -0.014, 
        "time": "2016-06-15T06:10:24.000Z", 
        "hightempinsulin": 0, 
        "bolussnooze": 0, 
        "iob": -0.014
      }, 
      {
        "netbasalinsulin": -0.45, 
        "activity": -0.0009, 
        "basaliob": -0.01, 
        "time": "2016-06-15T06:15:24.000Z", 
        "hightempinsulin": 0, 
        "bolussnooze": 0, 
        "iob": -0.01
      }, 
      {
        "netbasalinsulin": -0.4, 
        "activity": -0.0007, 
        "basaliob": -0.006, 
        "time": "2016-06-15T06:20:24.000Z", 
        "hightempinsulin": 0, 
        "bolussnooze": 0, 
        "iob": -0.006
      }, 
      {
        "netbasalinsulin": -0.35, 
        "activity": -0.0005, 
        "basaliob": -0.004, 
        "time": "2016-06-15T06:25:24.000Z", 
        "hightempinsulin": 0, 
        "bolussnooze": 0, 
        "iob": -0.004
      }
    ], 
    "enacted": {
      "bg": 171, 
      "temp": "absolute", 
      "snoozeBG": 9, 
      "recieved": true, 
      "predBGs": {
        "aCOB": [
          171, 
          169, 
          167, 
          165, 
          162, 
          159, 
          155, 
          152, 
          149, 
          146, 
          144, 
          142, 
          141, 
          140, 
          140, 
          140, 
          140, 
          141, 
          142, 
          143, 
          145, 
          146, 
          148, 
          150, 
          152, 
          153, 
          155, 
          157, 
          158, 
          159, 
          160, 
          160, 
          160, 
          161
        ], 
        "IOB": [
          171, 
          160, 
          148, 
          137, 
          125, 
          114, 
          102, 
          91, 
          80, 
          71, 
          62, 
          54, 
          47, 
          40, 
          39
        ]
      }, 
      "reason": "COB: 36, Dev: -9, BGI: -9.8, ISF: 67.8, Target: 107; Eventual BG 9<107, setting -4.952U/hr", 
      "rate": 0, 
      "COB": 36, 
      "eventualBG": 9, 
      "timestamp": "2016-06-15T03:26:47.000Z", 
      "duration": 30, 
      "tick": -8, 
      "IOB": 2.259
    }
  }, 
  "mmtune": {
    "scanDetails": [
      [
        "916.564", 
        5, 
        -72
      ], 
      [
        "916.588", 
        5, 
        -63
      ], 
      [
        "916.612", 
        5, 
        -62
      ], 
      [
        "916.636", 
        5, 
        -63
      ], 
      [
        "916.660", 
        5, 
        -63
      ], 
      [
        "916.684", 
        5, 
        -64
      ], 
      [
        "916.708", 
        5, 
        -73
      ]
    ], 
    "setFreq": 916.612, 
    "timestamp": "2016-06-15T03:30:41.000Z", 
    "usedDefault": false
  }
}