{
  "device": "openaps://indy-e1", 
  "pump": {
    "battery": {
      "status": "normal", 
      "voltage": 1.43
    }, 
    "status": {
      "status": "normal", 
      "timestamp": "2016-06-16T22:05:51.000Z", 
      "bolusing": false, 
      "suspended": false
    }, 
    "reservoir": 75.6, 
    "clock": "2016-06-16T15:04:55-07:00"
  }, 
  "openaps": {
    "suggested": {
      "bg": 181, 
      "temp": "absolute", 
      "snoozeBG": 46, 
      "timestamp": "2016-06-16T22:06:48.000Z", 
      "predBGs": {
        "aCOB": [
          181, 
          182, 
          181, 
          180, 
          178, 
          175, 
          171, 
          166, 
          161, 
          156, 
          150, 
          145, 
          139, 
          134, 
          129, 
          125, 
          121, 
          118, 
          115, 
          113, 
          110, 
          109, 
          107, 
          106, 
          105, 
          104, 
          104, 
          104, 
          104, 
          104, 
          105, 
          105, 
          105, 
          106
        ], 
        "IOB": [
          181, 
          172, 
          163, 
          155, 
          146, 
          137, 
          128, 
          119, 
          110, 
          102, 
          94, 
          87, 
          81, 
          76, 
          71, 
          67, 
          63, 
          60, 
          57, 
          55, 
          52, 
          51, 
          49, 
          48, 
          47, 
          46, 
          46, 
          46, 
          46, 
          46, 
          47, 
          47, 
          47, 
          48
        ]
      }, 
      "reason": "COB: 14, Dev: -19, BGI: -5.86, ISF: 80.8, Target: 116; Eventual BG 40<116, setting -2.965U/hr, but 22m left and 0 ~ req 0U/hr: no action required", 
      "COB": 14, 
      "eventualBG": 40, 
      "tick": -6, 
      "IOB": 1.509
    }, 
    "iob": [
      {
        "netbasalinsulin": 0.8, 
        "activity": 0.0145, 
        "basaliob": 0.621, 
        "time": "2016-06-16T22:04:55.000Z", 
        "hightempinsulin": 1.25, 
        "bolussnooze": 0.053, 
        "iob": 1.509
      }, 
      {
        "netbasalinsulin": 0.75, 
        "activity": 0.0154, 
        "basaliob": 0.524, 
        "time": "2016-06-16T22:09:55.000Z", 
        "hightempinsulin": 1.25, 
        "bolussnooze": 0.007, 
        "iob": 1.382
      }, 
      {
        "netbasalinsulin": 0.75, 
        "activity": 0.0163, 
        "basaliob": 0.477, 
        "time": "2016-06-16T22:14:55.000Z", 
        "hightempinsulin": 1.25, 
        "bolussnooze": 0, 
        "iob": 1.3
      }, 
      {
        "netbasalinsulin": 0.75, 
        "activity": 0.0171, 
        "basaliob": 0.38, 
        "time": "2016-06-16T22:19:55.000Z", 
        "hightempinsulin": 1.25, 
        "bolussnooze": 0, 
        "iob": 1.165
      }, 
      {
        "netbasalinsulin": 0.7, 
        "activity": 0.0178, 
        "basaliob": 0.283, 
        "time": "2016-06-16T22:24:55.000Z", 
        "hightempinsulin": 1.25, 
        "bolussnooze": 0, 
        "iob": 1.026
      }, 
      {
        "netbasalinsulin": 0.75, 
        "activity": 0.0184, 
        "basaliob": 0.236, 
        "time": "2016-06-16T22:29:55.000Z", 
        "hightempinsulin": 1.25, 
        "bolussnooze": 0, 
        "iob": 0.934
      }, 
      {
        "netbasalinsulin": 0.8, 
        "activity": 0.0188, 
        "basaliob": 0.192, 
        "time": "2016-06-16T22:34:55.000Z", 
        "hightempinsulin": 1.25, 
        "bolussnooze": 0, 
        "iob": 0.84
      }, 
      {
        "netbasalinsulin": 0.85, 
        "activity": 0.019, 
        "basaliob": 0.15, 
        "time": "2016-06-16T22:39:55.000Z", 
        "hightempinsulin": 1.25, 
        "bolussnooze": 0, 
        "iob": 0.745
      }, 
      {
        "netbasalinsulin": 0.85, 
        "activity": 0.0187, 
        "basaliob": 0.111, 
        "time": "2016-06-16T22:44:55.000Z", 
        "hightempinsulin": 1.25, 
        "bolussnooze": 0, 
        "iob": 0.651
      }, 
      {
        "netbasalinsulin": 0.9, 
        "activity": 0.0174, 
        "basaliob": 0.076, 
        "time": "2016-06-16T22:49:55.000Z", 
        "hightempinsulin": 1.25, 
        "bolussnooze": 0, 
        "iob": 0.564
      }, 
      {
        "netbasalinsulin": 0.95, 
        "activity": 0.016, 
        "basaliob": 0.045, 
        "time": "2016-06-16T22:54:55.000Z", 
        "hightempinsulin": 1.25, 
        "bolussnooze": 0, 
        "iob": 0.484
      }, 
      {
        "netbasalinsulin": 1, 
        "activity": 0.0147, 
        "basaliob": 0.019, 
        "time": "2016-06-16T22:59:55.000Z", 
        "hightempinsulin": 1.25, 
        "bolussnooze": 0, 
        "iob": 0.41
      }, 
      {
        "netbasalinsulin": 1, 
        "activity": 0.0133, 
        "basaliob": -0.003, 
        "time": "2016-06-16T23:04:55.000Z", 
        "hightempinsulin": 1.25, 
        "bolussnooze": 0, 
        "iob": 0.344
      }, 
      {
        "netbasalinsulin": 0.95, 
        "activity": 0.0119, 
        "basaliob": -0.021, 
        "time": "2016-06-16T23:09:55.000Z", 
        "hightempinsulin": 1.2, 
        "bolussnooze": 0, 
        "iob": 0.284
      }, 
      {
        "netbasalinsulin": 0.95, 
        "activity": 0.0106, 
        "basaliob": -0.035, 
        "time": "2016-06-16T23:14:55.000Z", 
        "hightempinsulin": 1.2, 
        "bolussnooze": 0, 
        "iob": 0.231
      }, 
      {
        "netbasalinsulin": 0.9, 
        "activity": 0.0094, 
        "basaliob": -0.046, 
        "time": "2016-06-16T23:19:55.000Z", 
        "hightempinsulin": 1.15, 
        "bolussnooze": 0, 
        "iob": 0.184
      }, 
      {
        "netbasalinsulin": 0.85, 
        "activity": 0.0082, 
        "basaliob": -0.053, 
        "time": "2016-06-16T23:24:55.000Z", 
        "hightempinsulin": 1.1, 
        "bolussnooze": 0, 
        "iob": 0.143
      }, 
      {
        "netbasalinsulin": 0.75, 
        "activity": 0.0071, 
        "basaliob": -0.058, 
        "time": "2016-06-16T23:29:55.000Z", 
        "hightempinsulin": 1, 
        "bolussnooze": 0, 
        "iob": 0.108
      }, 
      {
        "netbasalinsulin": 0.7, 
        "activity": 0.0061, 
        "basaliob": -0.06, 
        "time": "2016-06-16T23:34:55.000Z", 
        "hightempinsulin": 0.95, 
        "bolussnooze": 0, 
        "iob": 0.077
      }, 
      {
        "netbasalinsulin": 0.6, 
        "activity": 0.0053, 
        "basaliob": -0.061, 
        "time": "2016-06-16T23:39:55.000Z", 
        "hightempinsulin": 0.85, 
        "bolussnooze": 0, 
        "iob": 0.051
      }, 
      {
        "netbasalinsulin": 0.5, 
        "activity": 0.0044, 
        "basaliob": -0.06, 
        "time": "2016-06-16T23:44:55.000Z", 
        "hightempinsulin": 0.75, 
        "bolussnooze": 0, 
        "iob": 0.029
      }, 
      {
        "netbasalinsulin": 0.4, 
        "activity": 0.0037, 
        "basaliob": -0.058, 
        "time": "2016-06-16T23:49:55.000Z", 
        "hightempinsulin": 0.65, 
        "bolussnooze": 0, 
        "iob": 0.011
      }, 
      {
        "netbasalinsulin": 0.3, 
        "activity": 0.003, 
        "basaliob": -0.055, 
        "time": "2016-06-16T23:54:55.000Z", 
        "hightempinsulin": 0.55, 
        "bolussnooze": 0, 
        "iob": -0.004
      }, 
      {
        "netbasalinsulin": 0.3, 
        "activity": 0.0023, 
        "basaliob": -0.051, 
        "time": "2016-06-16T23:59:55.000Z", 
        "hightempinsulin": 0.55, 
        "bolussnooze": 0, 
        "iob": -0.015
      }, 
      {
        "netbasalinsulin": 0.3, 
        "activity": 0.0016, 
        "basaliob": -0.047, 
        "time": "2016-06-17T00:04:55.000Z", 
        "hightempinsulin": 0.55, 
        "bolussnooze": 0, 
        "iob": -0.023
      }, 
      {
        "netbasalinsulin": 0.25, 
        "activity": 0.0009, 
        "basaliob": -0.041, 
        "time": "2016-06-17T00:09:55.000Z", 
        "hightempinsulin": 0.5, 
        "bolussnooze": 0, 
        "iob": -0.028
      }, 
      {
        "netbasalinsulin": 0.1, 
        "activity": 0.0003, 
        "basaliob": -0.035, 
        "time": "2016-06-17T00:14:55.000Z", 
        "hightempinsulin": 0.35, 
        "bolussnooze": 0, 
        "iob": -0.029
      }, 
      {
        "netbasalinsulin": 0, 
        "activity": -0.0003, 
        "basaliob": -0.03, 
        "time": "2016-06-17T00:19:55.000Z", 
        "hightempinsulin": 0.25, 
        "bolussnooze": 0, 
        "iob": -0.028
      }, 
      {
        "netbasalinsulin": -0.15, 
        "activity": -0.0008, 
        "basaliob": -0.024, 
        "time": "2016-06-17T00:24:55.000Z", 
        "hightempinsulin": 0.1, 
        "bolussnooze": 0, 
        "iob": -0.024
      }, 
      {
        "netbasalinsulin": -0.25, 
        "activity": -0.001, 
        "basaliob": -0.019, 
        "time": "2016-06-17T00:29:55.000Z", 
        "hightempinsulin": 0, 
        "bolussnooze": 0, 
        "iob": -0.019
      }, 
      {
        "netbasalinsulin": -0.25, 
        "activity": -0.0009, 
        "basaliob": -0.014, 
        "time": "2016-06-17T00:34:55.000Z", 
        "hightempinsulin": 0, 
        "bolussnooze": 0, 
        "iob": -0.014
      }, 
      {
        "netbasalinsulin": -0.25, 
        "activity": -0.0008, 
        "basaliob": -0.01, 
        "time": "2016-06-17T00:39:55.000Z", 
        "hightempinsulin": 0, 
        "bolussnooze": 0, 
        "iob": -0.01
      }, 
      {
        "netbasalinsulin": -0.25, 
        "activity": -0.0006, 
        "basaliob": -0.007, 
        "time": "2016-06-17T00:44:55.000Z", 
        "hightempinsulin": 0, 
        "bolussnooze": 0, 
        "iob": -0.007
      }, 
      {
        "netbasalinsulin": -0.25, 
        "activity": -0.0005, 
        "basaliob": -0.005, 
        "time": "2016-06-17T00:49:55.000Z", 
        "hightempinsulin": 0, 
        "bolussnooze": 0, 
        "iob": -0.005
      }, 
      {
        "netbasalinsulin": -0.25, 
        "activity": -0.0004, 
        "basaliob": -0.003, 
        "time": "2016-06-17T00:54:55.000Z", 
        "hightempinsulin": 0, 
        "bolussnooze": 0, 
        "iob": -0.003
      }, 
      {
        "netbasalinsulin": -0.2, 
        "activity": -0.0003, 
        "basaliob": -0.001, 
        "time": "2016-06-17T00:59:55.000Z", 
        "hightempinsulin": 0, 
        "bolussnooze": 0, 
        "iob": -0.001
      }
    ], 
    "enacted": {
      "bg": 193, 
      "temp": "absolute", 
      "snoozeBG": 85, 
      "recieved": true, 
      "predBGs": {
        "aCOB": [
          193, 
          188, 
          183, 
          177, 
          172, 
          166, 
          159, 
          153, 
          146, 
          139, 
          133, 
          126, 
          120, 
          114, 
          108, 
          102, 
          96, 
          91, 
          86, 
          82, 
          78, 
          74, 
          71, 
          69, 
          66, 
          64, 
          63, 
          62, 
          61, 
          60, 
          60, 
          59
        ], 
        "IOB": [
          193, 
          179, 
          165, 
          152, 
          139, 
          126, 
          114, 
          102, 
          91, 
          81, 
          71, 
          62, 
          55, 
          47, 
          41, 
          39
        ]
      }, 
      "reason": "COB: 16, Dev: 2, BGI: -4.97, ISF: 80.8, Target: 116; Eventual BG 54<116, setting -1.035U/hr", 
      "rate": 0, 
      "COB": 16, 
      "eventualBG": 54, 
      "timestamp": "2016-06-16T21:57:22.000Z", 
      "duration": 30, 
      "tick": -15, 
      "IOB": 1.74
    }
  }, 
  "mmtune": {
    "scanDetails": [
      [
        "916.564", 
        4, 
        -91
      ], 
      [
        "916.588", 
        1, 
        -95
      ], 
      [
        "916.612", 
        2, 
        -91
      ], 
      [
        "916.636", 
        1, 
        -95
      ], 
      [
        "916.660", 
        4, 
        -72
      ], 
      [
        "916.684", 
        3, 
        -81
      ], 
      [
        "916.708", 
        4, 
        -81
      ]
    ], 
    "setFreq": 916.66, 
    "timestamp": "2016-06-16T22:05:10.000Z", 
    "usedDefault": false
  }
}